{
  "id": "alphabet",
  "title": "Letter Land",
  "stage": 2,
  "description": "The 26 letters: name, sound, and a friendly example word for each.",
  "items": [
    {"id": "A", "label": "A", "lower": "a", "name": "ay", "sound": "ah", "word": "Apple", "emoji": "🍎", "color": "#FF6B6B", "narration": "A. Ah. Apple."},
    {"id": "B", "label": "B", "lower": "b", "name": "bee", "sound": "buh", "word": "Ball", "emoji": "⚽", "color": "#5DC1F0", "narration": "B. Buh. Ball."},
    {"id": "C", "label": "C", "lower": "c", "name": "see", "sound": "kuh", "word": "Cat", "emoji": "🐱", "color": "#FF9F1C", "narration": "C. Kuh. Cat."},
    {"id": "D", "label": "D", "lower": "d", "name": "dee", "sound": "duh", "word": "Dog", "emoji": "🐶", "color": "#3DDC97", "narration": "D. Duh. Dog."},
    {"id": "E", "label": "E", "lower": "e", "name": "ee", "sound": "eh", "word": "Egg", "emoji": "🥚", "color": "#9B5DE5", "narration": "E. Eh. Egg."},
    {"id": "F", "label": "F", "lower": "f", "name": "eff", "sound": "fff", "word": "Fish", "emoji": "🐟", "color": "#2E9BD6", "narration": "F. Fff. Fish."},
    {"id": "G", "label": "G", "lower": "g", "name": "jee", "sound": "guh", "word": "Goat", "emoji": "🐐", "color": "#FF8FB1", "narration": "G. Guh. Goat."},
    {"id": "H", "label": "H", "lower": "h", "name": "aych", "sound": "huh", "word": "Hat", "emoji": "🎩", "color": "#FFD23F", "narration": "H. Huh. Hat."},
    {"id": "I", "label": "I", "lower": "i", "name": "eye", "sound": "ih", "word": "Igloo", "emoji": "🛖", "color": "#7AC74F", "narration": "I. Ih. Igloo."},
    {"id": "J", "label": "J", "lower": "j", "name": "jay", "sound": "juh", "word": "Jam", "emoji": "🍓", "color": "#FF6B6B", "narration": "J. Juh. Jam."},
    {"id": "K", "label": "K", "lower": "k", "name": "kay", "sound": "kuh", "word": "Kite", "emoji": "🪁", "color": "#5DC1F0", "narration": "K. Kuh. Kite."},
    {"id": "L", "label": "L", "lower": "l", "name": "ell", "sound": "lll", "word": "Lion", "emoji": "🦁", "color": "#FF9F1C", "narration": "L. Lll. Lion."},
    {"id": "M", "label": "M", "lower": "m", "name": "em", "sound": "mmm", "word": "Moon", "emoji": "🌙", "color": "#3DDC97", "narration": "M. Mmm. Moon."},
    {"id": "N", "label": "N", "lower": "n", "name": "en", "sound": "nnn", "word": "Nest", "emoji": "🪺", "color": "#9B5DE5", "narration": "N. Nnn. Nest."},
    {"id": "O", "label": "O", "lower": "o", "name": "oh", "sound": "oh", "word": "Orange", "emoji": "🍊", "color": "#2E9BD6", "narration": "O. Oh. Orange."},
    {"id": "P", "label": "P", "lower": "p", "name": "pee", "sound": "puh", "word": "Pig", "emoji": "🐷", "color": "#FF8FB1", "narration": "P. Puh. Pig."},
    {"id": "Q", "label": "Q", "lower": "q", "name": "cue", "sound": "kwuh", "word": "Queen", "emoji": "👑", "color": "#FFD23F", "narration": "Q. Kwuh. Queen."},
    {"id": "R", "label": "R", "lower": "r", "name": "arr", "sound": "rrr", "word": "Rabbit", "emoji": "🐰", "color": "#7AC74F", "narration": "R. Rrr. Rabbit."},
    {"id": "S", "label": "S", "lower": "s", "name": "ess", "sound": "sss", "word": "Sun", "emoji": "☀️", "color": "#FF6B6B", "narration": "S. Sss. Sun."},
    {"id": "T", "label": "T", "lower": "t", "name": "tee", "sound": "tuh", "word": "Tree", "emoji": "🌳", "color": "#5DC1F0", "narration": "T. Tuh. Tree."},
    {"id": "U", "label": "U", "lower": "u", "name": "you", "sound": "uh", "word": "Umbrella", "emoji": "☂️", "color": "#FF9F1C", "narration": "U. Uh. Umbrella."},
    {"id": "V", "label": "V", "lower": "v", "name": "vee", "sound": "vvv", "word": "Van", "emoji": "🚐", "color": "#3DDC97", "narration": "V. Vvv. Van."},
    {"id": "W", "label": "W", "lower": "w", "name": "double-you", "sound": "wuh", "word": "Whale", "emoji": "🐋", "color": "#9B5DE5", "narration": "W. Wuh. Whale."},
    {"id": "X", "label": "X", "lower": "x", "name": "ex", "sound": "ks", "word": "Fox", "emoji": "🦊", "color": "#2E9BD6", "narration": "X. Ks. Fox."},
    {"id": "Y", "label": "Y", "lower": "y", "name": "why", "sound": "yuh", "word": "Yo-yo", "emoji": "🪀", "color": "#FF8FB1", "narration": "Y. Yuh. Yo-yo."},
    {"id": "Z", "label": "Z", "lower": "z", "name": "zee", "sound": "zzz", "word": "Zebra", "emoji": "🦓", "color": "#FFD23F", "narration": "Z. Zzz. Zebra."}
  ]
}
